streamlit_select_icons/__init__.py
streamlit_select_icons/frontend/build/bootstrap.min.css
streamlit_select_icons/frontend/build/index.html
streamlit_select_icons/frontend/build/assets/index-cYXFmee5.js
streamlit_select_icons-0.1.0.dist-info/licenses/LICENSE
streamlit_select_icons-0.1.0.dist-info/METADATA
streamlit_select_icons-0.1.0.dist-info/WHEEL
streamlit_select_icons-0.1.0.dist-info/top_level.txt
streamlit_select_icons-0.1.0.dist-info/RECORD
