Metadata-Version: 2.4
Name: streamlit-select-icons
Version: 0.1.0
Summary: Streamlit component that creates a selectable list of icons with labels.
Author-email: Andrew Ferguson <afdatatech@gmail.com>
License: MIT
Project-URL: Homepage, https://github.com/edt-andrew/streamlit-select-icons
Project-URL: Bug Reports, https://github.com/edt-andrew/streamlit-select-icons/issues
Project-URL: Source, https://github.com/edt-andrew/streamlit-select-icons
Keywords: streamlit,component,icons,ui,selection
Classifier: Development Status :: 3 - Alpha
Classifier: Intended Audience :: Developers
Classifier: License :: OSI Approved :: MIT License
Classifier: Programming Language :: Python :: 3
Classifier: Programming Language :: Python :: 3.11
Classifier: Programming Language :: Python :: 3.12
Classifier: Topic :: Software Development :: Libraries :: Python Modules
Classifier: Topic :: Software Development :: User Interfaces
Classifier: Topic :: Internet :: WWW/HTTP :: Dynamic Content
Classifier: Topic :: Multimedia :: Graphics
Requires-Python: >=3.11
License-File: LICENSE
Requires-Dist: streamlit>=0.63
Provides-Extra: dev
Requires-Dist: wheel; extra == "dev"
Requires-Dist: pytest==7.4.0; extra == "dev"
Requires-Dist: playwright==1.48.0; extra == "dev"
Requires-Dist: requests==2.31.0; extra == "dev"
Requires-Dist: pytest-playwright-snapshot==1.0; extra == "dev"
Requires-Dist: pytest-rerunfailures==12.0; extra == "dev"
Dynamic: license-file
